xchainpy2_mayachain/__init__.py
xchainpy2_mayachain/client.py
xchainpy2_mayachain/const.py
xchainpy2_mayachain/models.py
xchainpy2_mayachain/utils.py
xchainpy2_mayachain/mrc20/__init__.py
xchainpy2_mayachain/mrc20/api.py
xchainpy2_mayachain/mrc20/const.py
xchainpy2_mayachain/mrc20/memo.py
xchainpy2_mayachain/mrc20/model.py
xchainpy2_mayachain/mrc20/utils.py
xchainpy2_mayachain/proto/__init__.py
xchainpy2_mayachain/proto/cosmos/__init__.py
xchainpy2_mayachain/proto/cosmos/base/__init__.py
xchainpy2_mayachain/proto/cosmos/base/v1beta1/__init__.py
xchainpy2_mayachain/proto/cosmos/base/v1beta1/coin_pb2.py
xchainpy2_mayachain/proto/cosmos/base/v1beta1/coin_pb2.pyi
xchainpy2_mayachain/proto/cosmos/base/v1beta1/coin_pb2_grpc.py
xchainpy2_mayachain/proto/gogoproto/__init__.py
xchainpy2_mayachain/proto/gogoproto/gogo_pb2.py
xchainpy2_mayachain/proto/gogoproto/gogo_pb2.pyi
xchainpy2_mayachain/proto/gogoproto/gogo_pb2_grpc.py
xchainpy2_mayachain/proto/mayachain/__init__.py
xchainpy2_mayachain/proto/mayachain/v1/__init__.py
xchainpy2_mayachain/proto/mayachain/v1/common/__init__.py
xchainpy2_mayachain/proto/mayachain/v1/common/common_pb2.py
xchainpy2_mayachain/proto/mayachain/v1/common/common_pb2.pyi
xchainpy2_mayachain/proto/mayachain/v1/common/common_pb2_grpc.py
xchainpy2_mayachain/proto/mayachain/v1/x/__init__.py
xchainpy2_mayachain/proto/mayachain/v1/x/mayachain/__init__.py
xchainpy2_mayachain/proto/mayachain/v1/x/mayachain/types/__init__.py
xchainpy2_mayachain/proto/mayachain/v1/x/mayachain/types/msg_deposit_pb2.py
xchainpy2_mayachain/proto/mayachain/v1/x/mayachain/types/msg_deposit_pb2.pyi
xchainpy2_mayachain/proto/mayachain/v1/x/mayachain/types/msg_deposit_pb2_grpc.py
xchainpy2_mayachain/proto/mayachain/v1/x/mayachain/types/msg_send_pb2.py
xchainpy2_mayachain/proto/mayachain/v1/x/mayachain/types/msg_send_pb2.pyi
xchainpy2_mayachain/proto/mayachain/v1/x/mayachain/types/msg_send_pb2_grpc.py
xchainpy2_mayachain/tests/test_basic_mc.py
xchainpy2_mayachain/tests/test_fee.py
xchainpy2_mayachain-0.0.17.dist-info/LICENSE
xchainpy2_mayachain-0.0.17.dist-info/METADATA
xchainpy2_mayachain-0.0.17.dist-info/WHEEL
xchainpy2_mayachain-0.0.17.dist-info/top_level.txt
xchainpy2_mayachain-0.0.17.dist-info/RECORD
